data_copilot/__init__.py
data_copilot/_version.py
data_copilot/configure.py
data_copilot/main.py
data_copilot/backend/__init__.py
data_copilot/backend/main.py
data_copilot/backend/artifacts/__init__.py
data_copilot/backend/artifacts/artifact.py
data_copilot/backend/celery/__init__.py
data_copilot/backend/celery/app.py
data_copilot/backend/config/__init__.py
data_copilot/backend/config/config.py
data_copilot/backend/crud/__init__.py
data_copilot/backend/crud/artifacts.py
data_copilot/backend/crud/chats.py
data_copilot/backend/crud/users.py
data_copilot/backend/database/__init__.py
data_copilot/backend/database/psql.py
data_copilot/backend/dependencies/__init__.py
data_copilot/backend/dependencies/artifacts.py
data_copilot/backend/dependencies/authentication.py
data_copilot/backend/dependencies/chats.py
data_copilot/backend/dependencies/user_management.py
data_copilot/backend/routers/__init__.py
data_copilot/backend/routers/artifacts.py
data_copilot/backend/routers/chats.py
data_copilot/backend/routers/health.py
data_copilot/backend/routers/token.py
data_copilot/backend/routers/users.py
data_copilot/backend/routers/admin/__init__.py
data_copilot/backend/routers/admin/admin.py
data_copilot/backend/routers/admin/groups.py
data_copilot/backend/routers/admin/users.py
data_copilot/backend/schemas/__init__.py
data_copilot/backend/schemas/artifacts.py
data_copilot/backend/schemas/authentication.py
data_copilot/backend/schemas/chats.py
data_copilot/backend/setup/__init__.py
data_copilot/backend/setup/setup.py
data_copilot/backend/tests/__init__.py
data_copilot/backend/tests/utils.py
data_copilot/backend/tests/routers_tests/test_admin.py
data_copilot/backend/tests/routers_tests/test_artifacts.py
data_copilot/backend/tests/routers_tests/test_user.py
data_copilot/backend/utils/__init__.py
data_copilot/backend/utils/authentication.py
data_copilot/backend/utils/security.py
data_copilot/celery_app/__init__.py
data_copilot/celery_app/worker.py
data_copilot-0.1.2.dist-info/LICENSE.txt
data_copilot-0.1.2.dist-info/METADATA
data_copilot-0.1.2.dist-info/WHEEL
data_copilot-0.1.2.dist-info/entry_points.txt
data_copilot-0.1.2.dist-info/top_level.txt
data_copilot-0.1.2.dist-info/RECORD
