Metadata-Version: 2.1
Name: data-copilot
Version: 0.1.2
Summary: The data_copilot web application
Author-email: Modulos AG <contact@modulos.ai>
Project-URL: Homepage, https://github.com/Modulos/data_copilot/
Project-URL: Bug Reports, https://github.com/Modulos/data_copilot/issues
Project-URL: Source, https://github.com/Modulos/data_copilot/
Keywords: data_copilot
Classifier: Development Status :: 2 - Pre-Alpha
Classifier: Intended Audience :: Developers
Classifier: Natural Language :: English
Classifier: Programming Language :: Python :: 3.10
Classifier: Programming Language :: Python :: 3.11
Requires-Python: >=3.10
License-File: LICENSE.txt
Requires-Dist: aiohttp (>=3.8.3)
Requires-Dist: alembic (>=1.10.2)
Requires-Dist: bcrypt (>=4.0.1)
Requires-Dist: build (>=0.10.0)
Requires-Dist: celery (>=5.2.7)
Requires-Dist: click (>=8.1.3)
Requires-Dist: colorama (>=0.4.6)
Requires-Dist: email-validator (>=1.3.0)
Requires-Dist: fastapi-sso (>=0.6.4)
Requires-Dist: fastapi (>=0.86.0)
Requires-Dist: Flask (>=2.3.2)
Requires-Dist: fsspec (>=2023.1.0)
Requires-Dist: langchain (>=0.0.179)
Requires-Dist: numpy (>=1.23.2)
Requires-Dist: openai (>=0.27)
Requires-Dist: openpyxl (>=3.1.1)
Requires-Dist: pandas (>=1.5.3)
Requires-Dist: passlib (>=1.7.4)
Requires-Dist: psycopg2-binary (>=2.9.5)
Requires-Dist: pydantic (>=1.10.4)
Requires-Dist: python-dotenv (>=0.21.1)
Requires-Dist: python-jose (>=3.3.0)
Requires-Dist: python-multipart (>=0.0.5)
Requires-Dist: redis (>=4.4.2)
Requires-Dist: simplejson (>=3.18.3)
Requires-Dist: sqlalchemy (>=2.0.4)
Requires-Dist: tabulate (==0.9.0)
Requires-Dist: uvicorn (>=0.20.0)
Requires-Dist: watchdog (>=2.2.1)
Requires-Dist: xlrd (>=2.0.1)
Provides-Extra: dev
Requires-Dist: black (<=23.3.0,>=23.3.0) ; extra == 'dev'
Requires-Dist: click (>=8.1.3) ; extra == 'dev'
Requires-Dist: ddt (>=1.6.0) ; extra == 'dev'
Requires-Dist: pytest (>=7.2.2) ; extra == 'dev'
Requires-Dist: tox (>=4.4.8) ; extra == 'dev'
Requires-Dist: xlwt (>=1.3.0) ; extra == 'dev'
